vat_algorithms_paritosh_101/VAT.py
vat_algorithms_paritosh_101/__init__.py
vat_algorithms_paritosh_101/example.py
vat_algorithms_paritosh_101/iVAT.py
vat_algorithms_paritosh_101-0.0.1.dist-info/METADATA
vat_algorithms_paritosh_101-0.0.1.dist-info/WHEEL
vat_algorithms_paritosh_101-0.0.1.dist-info/licenses/LICENSE
vat_algorithms_paritosh_101-0.0.1.dist-info/RECORD
