Metadata-Version: 2.3
Name: vat_algorithms_paritosh_101
Version: 0.0.1
Summary: Visual Assessment of Cluster Tendency (VAT) family of Algorithms
Project-URL: Homepage, https://github.com/pypa/sampleproject
Project-URL: Issues, https://github.com/pypa/sampleproject/issues
Author: Paritosh, Krishna Murthy
License-File: LICENSE
Classifier: License :: OSI Approved :: MIT License
Classifier: Operating System :: OS Independent
Classifier: Programming Language :: Python :: 3
Requires-Python: >=3.8
